{
	"id": "1lwvw875ZciycBS",
	"json": "{\"id\":\"1lwvw875ZciycBS\",\"url\":\"https://www.chestertons.co.uk/properties/lettings/status-available?page=3\",\"loadedUrl\":\"https://www.chestertons.co.uk/properties/lettings/status-available?page=3\",\"uniqueKey\":\"https://www.chestertons.co.uk/properties/lettings/status-available?page=3\",\"method\":\"GET\",\"noRetry\":false,\"retryCount\":0,\"errorMessages\":[],\"headers\":{},\"userData\":{\"pageNum\":3,\"isRental\":true,\"label\":\"LETTINGS_PAGE_3\",\"__crawlee\":{\"state\":4}},\"handledAt\":\"2026-02-20T14:16:30.824Z\"}",
	"method": "GET",
	"orderNo": null,
	"retryCount": 0,
	"uniqueKey": "https://www.chestertons.co.uk/properties/lettings/status-available?page=3",
	"url": "https://www.chestertons.co.uk/properties/lettings/status-available?page=3"
}