{
	"id": "6kpfdXEBgNCxtr1",
	"json": "{\"id\":\"6kpfdXEBgNCxtr1\",\"url\":\"https://www.chestertons.co.uk/properties/sales/status-available?page=80\",\"loadedUrl\":\"https://www.chestertons.co.uk/properties/sales/status-available?page=80\",\"uniqueKey\":\"https://www.chestertons.co.uk/properties/sales/status-available?page=80\",\"method\":\"GET\",\"noRetry\":false,\"retryCount\":0,\"errorMessages\":[],\"headers\":{},\"userData\":{\"pageNum\":80,\"isRental\":false,\"label\":\"SALES_PAGE_80\",\"__crawlee\":{\"state\":4}},\"handledAt\":\"2026-02-20T13:46:37.194Z\"}",
	"method": "GET",
	"orderNo": null,
	"retryCount": 0,
	"uniqueKey": "https://www.chestertons.co.uk/properties/sales/status-available?page=80",
	"url": "https://www.chestertons.co.uk/properties/sales/status-available?page=80"
}