{
	"id": "7TX2rL5nvWFndD7",
	"json": "{\"id\":\"7TX2rL5nvWFndD7\",\"url\":\"https://www.sequencehome.co.uk/properties/sales/page-1216\",\"uniqueKey\":\"https://www.sequencehome.co.uk/properties/sales/page-1216\",\"method\":\"GET\",\"noRetry\":false,\"retryCount\":0,\"errorMessages\":[],\"headers\":{},\"userData\":{\"pageNum\":1216,\"isRental\":false,\"label\":\"SALES_PAGE_1216\"}}",
	"method": "GET",
	"orderNo": 1772519917272,
	"retryCount": 0,
	"uniqueKey": "https://www.sequencehome.co.uk/properties/sales/page-1216",
	"url": "https://www.sequencehome.co.uk/properties/sales/page-1216"
}