{
	"id": "9WmRJXgn2Nh8OZk",
	"json": "{\"id\":\"9WmRJXgn2Nh8OZk\",\"url\":\"https://www.chestertons.co.uk/properties/sales/status-available?page=53\",\"uniqueKey\":\"https://www.chestertons.co.uk/properties/sales/status-available?page=53\",\"method\":\"GET\",\"noRetry\":false,\"retryCount\":0,\"errorMessages\":[],\"headers\":{},\"userData\":{\"pageNum\":53,\"isRental\":false,\"label\":\"SALES_PAGE_53\"}}",
	"method": "GET",
	"orderNo": 1771822763020,
	"retryCount": 0,
	"uniqueKey": "https://www.chestertons.co.uk/properties/sales/status-available?page=53",
	"url": "https://www.chestertons.co.uk/properties/sales/status-available?page=53"
}