{
	"id": "CgMxLuWP1CxSjF9",
	"json": "{\"id\":\"CgMxLuWP1CxSjF9\",\"url\":\"https://www.leaders.co.uk/properties/to-rent/page-257/\",\"uniqueKey\":\"https://www.leaders.co.uk/properties/to-rent/page-257\",\"method\":\"GET\",\"noRetry\":false,\"retryCount\":0,\"errorMessages\":[],\"headers\":{},\"userData\":{\"pageNum\":257,\"isRental\":true,\"label\":\"RENTALS\"}}",
	"method": "GET",
	"orderNo": 1772081881588,
	"retryCount": 0,
	"uniqueKey": "https://www.leaders.co.uk/properties/to-rent/page-257",
	"url": "https://www.leaders.co.uk/properties/to-rent/page-257/"
}