{
	"id": "Fx704pQKy6ZsPcV",
	"json": "{\"id\":\"Fx704pQKy6ZsPcV\",\"url\":\"https://www.balgoresproperty.co.uk/properties-for-sale/essex-and-kent/?page=4\",\"uniqueKey\":\"https://www.balgoresproperty.co.uk/properties-for-sale/essex-and-kent?page=4\",\"method\":\"GET\",\"noRetry\":false,\"retryCount\":0,\"errorMessages\":[],\"headers\":{},\"userData\":{\"pageNum\":4,\"isRental\":false,\"label\":\"SALES\",\"totalPages\":20}}",
	"method": "GET",
	"orderNo": 1773993370795,
	"retryCount": 0,
	"uniqueKey": "https://www.balgoresproperty.co.uk/properties-for-sale/essex-and-kent?page=4",
	"url": "https://www.balgoresproperty.co.uk/properties-for-sale/essex-and-kent/?page=4"
}