{
	"id": "LewjplksImM8kam",
	"json": "{\"id\":\"LewjplksImM8kam\",\"url\":\"https://www.sequencehome.co.uk/properties/sales/page-82\",\"uniqueKey\":\"https://www.sequencehome.co.uk/properties/sales/page-82\",\"method\":\"GET\",\"noRetry\":false,\"retryCount\":0,\"errorMessages\":[],\"headers\":{},\"userData\":{\"pageNum\":82,\"isRental\":false,\"label\":\"SALES_PAGE_82\"}}",
	"method": "GET",
	"orderNo": 1772519912671,
	"retryCount": 0,
	"uniqueKey": "https://www.sequencehome.co.uk/properties/sales/page-82",
	"url": "https://www.sequencehome.co.uk/properties/sales/page-82"
}