{
	"id": "mDbHOQxqw4UU6f5",
	"json": "{\"id\":\"mDbHOQxqw4UU6f5\",\"url\":\"https://www.sequencehome.co.uk/properties/sales/page-1318\",\"uniqueKey\":\"https://www.sequencehome.co.uk/properties/sales/page-1318\",\"method\":\"GET\",\"noRetry\":false,\"retryCount\":0,\"errorMessages\":[],\"headers\":{},\"userData\":{\"pageNum\":1318,\"isRental\":false,\"label\":\"SALES_PAGE_1318\"}}",
	"method": "GET",
	"orderNo": 1772519918115,
	"retryCount": 0,
	"uniqueKey": "https://www.sequencehome.co.uk/properties/sales/page-1318",
	"url": "https://www.sequencehome.co.uk/properties/sales/page-1318"
}