{
	"id": "nM09jex1mlvRJMn",
	"json": "{\"id\":\"nM09jex1mlvRJMn\",\"url\":\"https://www.sequencehome.co.uk/properties/sales/page-768\",\"uniqueKey\":\"https://www.sequencehome.co.uk/properties/sales/page-768\",\"method\":\"GET\",\"noRetry\":false,\"retryCount\":0,\"errorMessages\":[],\"headers\":{},\"userData\":{\"pageNum\":768,\"isRental\":false,\"label\":\"SALES_PAGE_768\"}}",
	"method": "GET",
	"orderNo": 1772519915082,
	"retryCount": 0,
	"uniqueKey": "https://www.sequencehome.co.uk/properties/sales/page-768",
	"url": "https://www.sequencehome.co.uk/properties/sales/page-768"
}