{
	"id": "Nyu7NklIkcUihL5",
	"json": "{\"id\":\"Nyu7NklIkcUihL5\",\"url\":\"https://www.sequencehome.co.uk/properties/sales/page-1463\",\"uniqueKey\":\"https://www.sequencehome.co.uk/properties/sales/page-1463\",\"method\":\"GET\",\"noRetry\":false,\"retryCount\":0,\"errorMessages\":[],\"headers\":{},\"userData\":{\"pageNum\":1463,\"isRental\":false,\"label\":\"SALES_PAGE_1463\"}}",
	"method": "GET",
	"orderNo": 1772519921053,
	"retryCount": 0,
	"uniqueKey": "https://www.sequencehome.co.uk/properties/sales/page-1463",
	"url": "https://www.sequencehome.co.uk/properties/sales/page-1463"
}