{
	"id": "SSI9yffHfBdLvKI",
	"json": "{\"id\":\"SSI9yffHfBdLvKI\",\"url\":\"https://www.sequencehome.co.uk/properties/sales/page-998\",\"uniqueKey\":\"https://www.sequencehome.co.uk/properties/sales/page-998\",\"method\":\"GET\",\"noRetry\":false,\"retryCount\":0,\"errorMessages\":[],\"headers\":{},\"userData\":{\"pageNum\":998,\"isRental\":false,\"label\":\"SALES_PAGE_998\"}}",
	"method": "GET",
	"orderNo": 1772519915805,
	"retryCount": 0,
	"uniqueKey": "https://www.sequencehome.co.uk/properties/sales/page-998",
	"url": "https://www.sequencehome.co.uk/properties/sales/page-998"
}