{
  "requestsFinished": 15,
  "requestsFailed": 0,
  "requestsRetries": 0,
  "requestsFailedPerMinute": 0,
  "requestsFinishedPerMinute": 2,
  "requestMinDurationMillis": 6589,
  "requestMaxDurationMillis": 48424,
  "requestTotalFailedDurationMillis": 0,
  "requestTotalFinishedDurationMillis": 414462,
  "crawlerStartedAt": "2026-02-28T12:58:46.239Z",
  "crawlerFinishedAt": null,
  "statsPersistedAt": "2026-02-28T13:05:46.270Z",
  "crawlerRuntimeMillis": 420611,
  "crawlerLastStartTimestamp": 1772283525659,
  "requestRetryHistogram": [
    15
  ],
  "statsId": 0,
  "requestAvgFailedDurationMillis": null,
  "requestAvgFinishedDurationMillis": 27631,
  "requestTotalDurationMillis": 414462,
  "requestsTotal": 15,
  "requestsWithStatusCode": {
    "200": 15
  },
  "errors": {},
  "retryErrors": {}
}