{
  "usableSessionsCount": 16,
  "retiredSessionsCount": 0,
  "sessions": [
    {
      "id": "session_PC8WlruPYf",
      "cookieJar": {
        "version": "tough-cookie@6.0.0",
        "storeType": "MemoryCookieStore",
        "rejectPublicSuffixes": true,
        "enableLooseMode": false,
        "allowSpecialUseDomain": true,
        "prefixSecurity": "silent",
        "cookies": [
          {
            "key": "ASP.NET_SessionId",
            "value": "zr2zd3w3llbhxm1wi4ucamzi",
            "domain": "www.ableestates.com",
            "path": "/",
            "httpOnly": true,
            "hostOnly": true,
            "creation": "2026-03-05T07:12:59.975Z",
            "lastAccessed": "2026-03-05T07:12:59.975Z",
            "sameSite": "lax"
          }
        ]
      },
      "userData": {},
      "maxErrorScore": 3,
      "errorScoreDecrement": 0.5,
      "expiresAt": "2026-03-05T08:02:46.745Z",
      "createdAt": "2026-03-05T07:12:46.744Z",
      "usageCount": 1,
      "maxUsageCount": 50,
      "errorScore": 0
    },
    {
      "id": "session_hQBsLbjlUM",
      "cookieJar": {
        "version": "tough-cookie@6.0.0",
        "storeType": "MemoryCookieStore",
        "rejectPublicSuffixes": true,
        "enableLooseMode": false,
        "allowSpecialUseDomain": true,
        "prefixSecurity": "silent",
        "cookies": [
          {
            "key": "ASP.NET_SessionId",
            "value": "ryo2vio1enkyrxr0oryiak05",
            "domain": "www.ableestates.com",
            "path": "/",
            "httpOnly": true,
            "hostOnly": true,
            "creation": "2026-03-05T07:13:12.704Z",
            "lastAccessed": "2026-03-05T07:13:12.704Z",
            "sameSite": "lax"
          }
        ]
      },
      "userData": {},
      "maxErrorScore": 3,
      "errorScoreDecrement": 0.5,
      "expiresAt": "2026-03-05T08:03:05.644Z",
      "createdAt": "2026-03-05T07:13:05.644Z",
      "usageCount": 1,
      "maxUsageCount": 50,
      "errorScore": 0
    },
    {
      "id": "session_2lz3mXuFbx",
      "cookieJar": {
        "version": "tough-cookie@6.0.0",
        "storeType": "MemoryCookieStore",
        "rejectPublicSuffixes": true,
        "enableLooseMode": false,
        "allowSpecialUseDomain": true,
        "prefixSecurity": "silent",
        "cookies": [
          {
            "key": "ASP.NET_SessionId",
            "value": "5id32zhw0jr4pm42lf4vciwb",
            "domain": "www.ableestates.com",
            "path": "/",
            "httpOnly": true,
            "hostOnly": true,
            "creation": "2026-03-05T07:13:21.806Z",
            "lastAccessed": "2026-03-05T07:13:21.806Z",
            "sameSite": "lax"
          }
        ]
      },
      "userData": {},
      "maxErrorScore": 3,
      "errorScoreDecrement": 0.5,
      "expiresAt": "2026-03-05T08:03:15.463Z",
      "createdAt": "2026-03-05T07:13:15.463Z",
      "usageCount": 1,
      "maxUsageCount": 50,
      "errorScore": 0
    },
    {
      "id": "session_XxogdCl9If",
      "cookieJar": {
        "version": "tough-cookie@6.0.0",
        "storeType": "MemoryCookieStore",
        "rejectPublicSuffixes": true,
        "enableLooseMode": false,
        "allowSpecialUseDomain": true,
        "prefixSecurity": "silent",
        "cookies": [
          {
            "key": "ASP.NET_SessionId",
            "value": "vpqpltznjzsllg1frqsdqtnw",
            "domain": "www.ableestates.com",
            "path": "/",
            "httpOnly": true,
            "hostOnly": true,
            "creation": "2026-03-05T07:13:30.349Z",
            "lastAccessed": "2026-03-05T07:13:30.349Z",
            "sameSite": "lax"
          }
        ]
      },
      "userData": {},
      "maxErrorScore": 3,
      "errorScoreDecrement": 0.5,
      "expiresAt": "2026-03-05T08:03:29.128Z",
      "createdAt": "2026-03-05T07:13:29.128Z",
      "usageCount": 1,
      "maxUsageCount": 50,
      "errorScore": 0
    },
    {
      "id": "session_CXOoV6oBDv",
      "cookieJar": {
        "version": "tough-cookie@6.0.0",
        "storeType": "MemoryCookieStore",
        "rejectPublicSuffixes": true,
        "enableLooseMode": false,
        "allowSpecialUseDomain": true,
        "prefixSecurity": "silent",
        "cookies": [
          {
            "key": "ASP.NET_SessionId",
            "value": "3i53n2grw1jneo53qnyloxdz",
            "domain": "www.ableestates.com",
            "path": "/",
            "httpOnly": true,
            "hostOnly": true,
            "creation": "2026-03-05T07:13:35.223Z",
            "lastAccessed": "2026-03-05T07:13:35.223Z",
            "sameSite": "lax"
          }
        ]
      },
      "userData": {},
      "maxErrorScore": 3,
      "errorScoreDecrement": 0.5,
      "expiresAt": "2026-03-05T08:03:33.698Z",
      "createdAt": "2026-03-05T07:13:33.698Z",
      "usageCount": 1,
      "maxUsageCount": 50,
      "errorScore": 0
    },
    {
      "id": "session_DgdmeirTMp",
      "cookieJar": {
        "version": "tough-cookie@6.0.0",
        "storeType": "MemoryCookieStore",
        "rejectPublicSuffixes": true,
        "enableLooseMode": false,
        "allowSpecialUseDomain": true,
        "prefixSecurity": "silent",
        "cookies": [
          {
            "key": "ASP.NET_SessionId",
            "value": "5at1pa4jhulb4r11dtmlnasd",
            "domain": "www.ableestates.com",
            "path": "/",
            "httpOnly": true,
            "hostOnly": true,
            "creation": "2026-03-05T07:13:45.322Z",
            "lastAccessed": "2026-03-05T07:13:45.322Z",
            "sameSite": "lax"
          }
        ]
      },
      "userData": {},
      "maxErrorScore": 3,
      "errorScoreDecrement": 0.5,
      "expiresAt": "2026-03-05T08:03:42.180Z",
      "createdAt": "2026-03-05T07:13:42.180Z",
      "usageCount": 1,
      "maxUsageCount": 50,
      "errorScore": 0
    },
    {
      "id": "session_I8uIlZv5Wq",
      "cookieJar": {
        "version": "tough-cookie@6.0.0",
        "storeType": "MemoryCookieStore",
        "rejectPublicSuffixes": true,
        "enableLooseMode": false,
        "allowSpecialUseDomain": true,
        "prefixSecurity": "silent",
        "cookies": [
          {
            "key": "ASP.NET_SessionId",
            "value": "5wzpuvl52jpc0gt0gtifktbk",
            "domain": "www.ableestates.com",
            "path": "/",
            "httpOnly": true,
            "hostOnly": true,
            "creation": "2026-03-05T07:13:48.540Z",
            "lastAccessed": "2026-03-05T07:13:48.540Z",
            "sameSite": "lax"
          }
        ]
      },
      "userData": {},
      "maxErrorScore": 3,
      "errorScoreDecrement": 0.5,
      "expiresAt": "2026-03-05T08:03:48.134Z",
      "createdAt": "2026-03-05T07:13:48.134Z",
      "usageCount": 1,
      "maxUsageCount": 50,
      "errorScore": 0
    },
    {
      "id": "session_1HPhZAkkRA",
      "cookieJar": {
        "version": "tough-cookie@6.0.0",
        "storeType": "MemoryCookieStore",
        "rejectPublicSuffixes": true,
        "enableLooseMode": false,
        "allowSpecialUseDomain": true,
        "prefixSecurity": "silent",
        "cookies": [
          {
            "key": "ASP.NET_SessionId",
            "value": "pxfwyjgfjif4qs1kv1d0hbee",
            "domain": "www.ableestates.com",
            "path": "/",
            "httpOnly": true,
            "hostOnly": true,
            "creation": "2026-03-05T07:13:54.052Z",
            "lastAccessed": "2026-03-05T07:13:54.052Z",
            "sameSite": "lax"
          }
        ]
      },
      "userData": {},
      "maxErrorScore": 3,
      "errorScoreDecrement": 0.5,
      "expiresAt": "2026-03-05T08:03:53.694Z",
      "createdAt": "2026-03-05T07:13:53.694Z",
      "usageCount": 1,
      "maxUsageCount": 50,
      "errorScore": 0
    },
    {
      "id": "session_hcYi3zd8QG",
      "cookieJar": {
        "version": "tough-cookie@6.0.0",
        "storeType": "MemoryCookieStore",
        "rejectPublicSuffixes": true,
        "enableLooseMode": false,
        "allowSpecialUseDomain": true,
        "prefixSecurity": "silent",
        "cookies": [
          {
            "key": "ASP.NET_SessionId",
            "value": "spg5g1wwiy1250pxomuzwqhe",
            "domain": "www.ableestates.com",
            "path": "/",
            "httpOnly": true,
            "hostOnly": true,
            "creation": "2026-03-05T07:13:56.981Z",
            "lastAccessed": "2026-03-05T07:13:56.981Z",
            "sameSite": "lax"
          }
        ]
      },
      "userData": {},
      "maxErrorScore": 3,
      "errorScoreDecrement": 0.5,
      "expiresAt": "2026-03-05T08:03:56.297Z",
      "createdAt": "2026-03-05T07:13:56.297Z",
      "usageCount": 1,
      "maxUsageCount": 50,
      "errorScore": 0
    },
    {
      "id": "session_2dFxEevQO9",
      "cookieJar": {
        "version": "tough-cookie@6.0.0",
        "storeType": "MemoryCookieStore",
        "rejectPublicSuffixes": true,
        "enableLooseMode": false,
        "allowSpecialUseDomain": true,
        "prefixSecurity": "silent",
        "cookies": [
          {
            "key": "ASP.NET_SessionId",
            "value": "ksmhlffglugaur3phsqfgj13",
            "domain": "www.ableestates.com",
            "path": "/",
            "httpOnly": true,
            "hostOnly": true,
            "creation": "2026-03-05T07:14:03.049Z",
            "lastAccessed": "2026-03-05T07:14:03.049Z",
            "sameSite": "lax"
          }
        ]
      },
      "userData": {},
      "maxErrorScore": 3,
      "errorScoreDecrement": 0.5,
      "expiresAt": "2026-03-05T08:04:01.985Z",
      "createdAt": "2026-03-05T07:14:01.985Z",
      "usageCount": 1,
      "maxUsageCount": 50,
      "errorScore": 0
    },
    {
      "id": "session_U3Cnv0X3WR",
      "cookieJar": {
        "version": "tough-cookie@6.0.0",
        "storeType": "MemoryCookieStore",
        "rejectPublicSuffixes": true,
        "enableLooseMode": false,
        "allowSpecialUseDomain": true,
        "prefixSecurity": "silent",
        "cookies": [
          {
            "key": "ASP.NET_SessionId",
            "value": "www00r4rmerfj55uyttm0sog",
            "domain": "www.ableestates.com",
            "path": "/",
            "httpOnly": true,
            "hostOnly": true,
            "creation": "2026-03-05T07:14:06.739Z",
            "lastAccessed": "2026-03-05T07:14:06.739Z",
            "sameSite": "lax"
          }
        ]
      },
      "userData": {},
      "maxErrorScore": 3,
      "errorScoreDecrement": 0.5,
      "expiresAt": "2026-03-05T08:04:05.448Z",
      "createdAt": "2026-03-05T07:14:05.448Z",
      "usageCount": 1,
      "maxUsageCount": 50,
      "errorScore": 0
    },
    {
      "id": "session_VQEV0oaUQA",
      "cookieJar": {
        "version": "tough-cookie@6.0.0",
        "storeType": "MemoryCookieStore",
        "rejectPublicSuffixes": true,
        "enableLooseMode": false,
        "allowSpecialUseDomain": true,
        "prefixSecurity": "silent",
        "cookies": [
          {
            "key": "ASP.NET_SessionId",
            "value": "2hgrz0nj1ghulyly3m2kjiwb",
            "domain": "www.ableestates.com",
            "path": "/",
            "httpOnly": true,
            "hostOnly": true,
            "creation": "2026-03-05T07:14:22.410Z",
            "lastAccessed": "2026-03-05T07:14:22.410Z",
            "sameSite": "lax"
          }
        ]
      },
      "userData": {},
      "maxErrorScore": 3,
      "errorScoreDecrement": 0.5,
      "expiresAt": "2026-03-05T08:04:12.250Z",
      "createdAt": "2026-03-05T07:14:12.250Z",
      "usageCount": 1,
      "maxUsageCount": 50,
      "errorScore": 0
    },
    {
      "id": "session_bDbJbTS4fZ",
      "cookieJar": {
        "version": "tough-cookie@6.0.0",
        "storeType": "MemoryCookieStore",
        "rejectPublicSuffixes": true,
        "enableLooseMode": false,
        "allowSpecialUseDomain": true,
        "prefixSecurity": "silent",
        "cookies": [
          {
            "key": "ASP.NET_SessionId",
            "value": "ayyhpjiotojc2dcil41hlnil",
            "domain": "www.ableestates.com",
            "path": "/",
            "httpOnly": true,
            "hostOnly": true,
            "creation": "2026-03-05T07:14:27.193Z",
            "lastAccessed": "2026-03-05T07:14:27.193Z",
            "sameSite": "lax"
          }
        ]
      },
      "userData": {},
      "maxErrorScore": 3,
      "errorScoreDecrement": 0.5,
      "expiresAt": "2026-03-05T08:04:26.425Z",
      "createdAt": "2026-03-05T07:14:26.425Z",
      "usageCount": 1,
      "maxUsageCount": 50,
      "errorScore": 0
    },
    {
      "id": "session_RfzQsqiYZQ",
      "cookieJar": {
        "version": "tough-cookie@6.0.0",
        "storeType": "MemoryCookieStore",
        "rejectPublicSuffixes": true,
        "enableLooseMode": false,
        "allowSpecialUseDomain": true,
        "prefixSecurity": "silent",
        "cookies": [
          {
            "key": "ASP.NET_SessionId",
            "value": "jolt4yvmq4n5cndxgcoyoc5d",
            "domain": "www.ableestates.com",
            "path": "/",
            "httpOnly": true,
            "hostOnly": true,
            "creation": "2026-03-05T07:14:32.814Z",
            "lastAccessed": "2026-03-05T07:14:32.814Z",
            "sameSite": "lax"
          }
        ]
      },
      "userData": {},
      "maxErrorScore": 3,
      "errorScoreDecrement": 0.5,
      "expiresAt": "2026-03-05T08:04:32.203Z",
      "createdAt": "2026-03-05T07:14:32.203Z",
      "usageCount": 1,
      "maxUsageCount": 50,
      "errorScore": 0
    },
    {
      "id": "session_b9n5cTej8t",
      "cookieJar": {
        "version": "tough-cookie@6.0.0",
        "storeType": "MemoryCookieStore",
        "rejectPublicSuffixes": true,
        "enableLooseMode": false,
        "allowSpecialUseDomain": true,
        "prefixSecurity": "silent",
        "cookies": [
          {
            "key": "ASP.NET_SessionId",
            "value": "5yvozvu444kkgbsskttjwyai",
            "domain": "www.ableestates.com",
            "path": "/",
            "httpOnly": true,
            "hostOnly": true,
            "creation": "2026-03-05T07:14:35.400Z",
            "lastAccessed": "2026-03-05T07:14:35.400Z",
            "sameSite": "lax"
          }
        ]
      },
      "userData": {},
      "maxErrorScore": 3,
      "errorScoreDecrement": 0.5,
      "expiresAt": "2026-03-05T08:04:34.928Z",
      "createdAt": "2026-03-05T07:14:34.928Z",
      "usageCount": 1,
      "maxUsageCount": 50,
      "errorScore": 0
    },
    {
      "id": "session_Fec0d1qmBp",
      "cookieJar": {
        "version": "tough-cookie@6.0.0",
        "storeType": "MemoryCookieStore",
        "rejectPublicSuffixes": true,
        "enableLooseMode": false,
        "allowSpecialUseDomain": true,
        "prefixSecurity": "silent",
        "cookies": [
          {
            "key": "ASP.NET_SessionId",
            "value": "fcipg10gsrhbwde5pgp5i1w5",
            "domain": "www.ableestates.com",
            "path": "/",
            "httpOnly": true,
            "hostOnly": true,
            "creation": "2026-03-05T07:14:41.722Z",
            "lastAccessed": "2026-03-05T07:14:41.722Z",
            "sameSite": "lax"
          }
        ]
      },
      "userData": {},
      "maxErrorScore": 3,
      "errorScoreDecrement": 0.5,
      "expiresAt": "2026-03-05T08:04:40.233Z",
      "createdAt": "2026-03-05T07:14:40.233Z",
      "usageCount": 0,
      "maxUsageCount": 50,
      "errorScore": 0
    }
  ]
}