{
	"id": "1zmqY3vdXFcbQdU",
	"json": "{\"id\":\"1zmqY3vdXFcbQdU\",\"url\":\"https://www.connells.co.uk/properties/sales/page-301\",\"uniqueKey\":\"https://www.connells.co.uk/properties/sales/page-301\",\"method\":\"GET\",\"noRetry\":false,\"retryCount\":0,\"errorMessages\":[],\"headers\":{},\"userData\":{\"pageNum\":301,\"isRental\":false,\"label\":\"SALES\"}}",
	"method": "GET",
	"orderNo": 1771916563669,
	"retryCount": 0,
	"uniqueKey": "https://www.connells.co.uk/properties/sales/page-301",
	"url": "https://www.connells.co.uk/properties/sales/page-301"
}