{
	"id": "Ahmc7ZAbFi3lik5",
	"json": "{\"id\":\"Ahmc7ZAbFi3lik5\",\"url\":\"https://www.connells.co.uk/properties/sales/page-257\",\"loadedUrl\":\"https://www.connells.co.uk/properties/sales/page-257\",\"uniqueKey\":\"https://www.connells.co.uk/properties/sales/page-257\",\"method\":\"GET\",\"noRetry\":false,\"retryCount\":0,\"errorMessages\":[],\"headers\":{},\"userData\":{\"pageNum\":257,\"isRental\":false,\"label\":\"SALES\",\"__crawlee\":{\"state\":4}},\"handledAt\":\"2026-02-24T07:12:28.666Z\"}",
	"method": "GET",
	"orderNo": null,
	"retryCount": 0,
	"uniqueKey": "https://www.connells.co.uk/properties/sales/page-257",
	"url": "https://www.connells.co.uk/properties/sales/page-257"
}