{
	"id": "G3qd1YHgMHo02Jq",
	"json": "{\"id\":\"G3qd1YHgMHo02Jq\",\"url\":\"https://www.beresfords.co.uk/find-a-property/to-rent/page/7/\",\"uniqueKey\":\"https://www.beresfords.co.uk/find-a-property/to-rent/page/7\",\"method\":\"GET\",\"noRetry\":false,\"retryCount\":0,\"errorMessages\":[],\"headers\":{},\"userData\":{\"pageNum\":7,\"isRental\":true,\"label\":\"LETTINGS\",\"processedDynamic\":true}}",
	"method": "GET",
	"orderNo": 1772803880298,
	"retryCount": 0,
	"uniqueKey": "https://www.beresfords.co.uk/find-a-property/to-rent/page/7",
	"url": "https://www.beresfords.co.uk/find-a-property/to-rent/page/7/"
}