{
	"id": "uevZmW4Bf2Ks08z",
	"json": "{\"id\":\"uevZmW4Bf2Ks08z\",\"url\":\"https://www.newtonfallowell.co.uk/properties/page-43/for-sale/in-the-midlands/?orderby=price_desc&radius=3\",\"uniqueKey\":\"https://www.newtonfallowell.co.uk/properties/page-43/for-sale/in-the-midlands?orderby=price_desc&radius=3\",\"method\":\"GET\",\"noRetry\":false,\"retryCount\":0,\"errorMessages\":[],\"headers\":{},\"userData\":{\"pageNum\":43,\"totalPages\":169,\"isRental\":false,\"label\":\"SALES\"}}",
	"method": "GET",
	"orderNo": 1772802137478,
	"retryCount": 0,
	"uniqueKey": "https://www.newtonfallowell.co.uk/properties/page-43/for-sale/in-the-midlands?orderby=price_desc&radius=3",
	"url": "https://www.newtonfallowell.co.uk/properties/page-43/for-sale/in-the-midlands/?orderby=price_desc&radius=3"
}