{
	"id": "ZqHymh1RHFslfrM",
	"json": "{\"id\":\"ZqHymh1RHFslfrM\",\"url\":\"https://www.mapestateagents.com/property-sales/properties-for-sale?start=156\",\"loadedUrl\":\"https://www.mapestateagents.com/property-sales/properties-for-sale?start=156\",\"uniqueKey\":\"https://www.mapestateagents.com/property-sales/properties-for-sale?start=156\",\"method\":\"GET\",\"noRetry\":false,\"retryCount\":0,\"errorMessages\":[],\"headers\":{},\"userData\":{\"isRental\":false,\"label\":\"SALES\",\"pageNum\":14,\"totalPages\":19,\"__crawlee\":{\"state\":4}},\"handledAt\":\"2026-03-06T11:13:20.925Z\"}",
	"method": "GET",
	"orderNo": null,
	"retryCount": 0,
	"uniqueKey": "https://www.mapestateagents.com/property-sales/properties-for-sale?start=156",
	"url": "https://www.mapestateagents.com/property-sales/properties-for-sale?start=156"
}